py_portfolio_arg/__init__.py
py_portfolio_arg/src/__init__.py
py_portfolio_arg/src/components/__init__.py
py_portfolio_arg/src/components/client.py
py_portfolio_arg/src/components/enums.py
py_portfolio_arg/src/components/exceptions.py
py_portfolio_arg/src/components/headers.py
py_portfolio_arg/src/components/urls.py
py_portfolio_arg/src/intraday.py
py_portfolio_arg-0.1.1.dist-info/METADATA
py_portfolio_arg-0.1.1.dist-info/WHEEL
py_portfolio_arg-0.1.1.dist-info/RECORD
