Metadata-Version: 2.1
Name: py_portfolio_arg
Version: 0.1.1
Summary: 
Author: Martín Basualdo
Author-email: 70729951+MartinBasualdo0@users.noreply.github.com
Requires-Python: >=3.9,<4.0
Classifier: Programming Language :: Python :: 3
Classifier: Programming Language :: Python :: 3.9
Classifier: Programming Language :: Python :: 3.10
Classifier: Programming Language :: Python :: 3.11
Classifier: Programming Language :: Python :: 3.12
Requires-Dist: beautifulsoup4 (>=4.12.3,<5.0.0)
Requires-Dist: bs4 (>=0.0.2,<0.0.3)
Requires-Dist: certifi (>=2024.7.4,<2025.0.0)
Requires-Dist: charset-normalizer (>=3.3.2,<4.0.0)
Requires-Dist: idna (>=3.7,<4.0)
Requires-Dist: numpy (>=2.0.1,<3.0.0)
Requires-Dist: pandas (>=2.2.2,<3.0.0)
Requires-Dist: python-dateutil (>=2.9.0.post0,<3.0.0)
Requires-Dist: python-dotenv (>=1.0.1,<2.0.0)
Requires-Dist: pytz (>=2024.1,<2025.0)
Requires-Dist: requests (>=2.32.3,<3.0.0)
Requires-Dist: simplejson (>=3.19.2,<4.0.0)
Requires-Dist: six (>=1.16.0,<2.0.0)
Requires-Dist: soupsieve (>=2.5,<3.0)
Requires-Dist: tzdata (>=2024.1,<2025.0)
Requires-Dist: urllib3 (>=2.2.2,<3.0.0)
Requires-Dist: xlsxwriter (>=3.2.0,<4.0.0)
